{
	"data":[
			{
			"id":"0",
			"club": {
					"end":"2012-06-30",
					"club_id":"0",
					"name":"SV Erbenheim Jugend"
				}
			}
		]
}

{
	"data":[
			{
			"id":"0",
			"club": {
					"end":"2007-06-30",
					"club_id":"0",
					"name":"SG Blau-Weiß Beelitz"
				}
			},
			{
			"id":"1",
			"club": {
					"end":"2008-06-30",
					"club_id":"0",
					"name":"ESV Lok Seddin"
				}
			},
			{
			"id":"2",
			"club": {
					"end":"2011-06-30",
					"club_id":"0",
					"name":"SpVgg Fortuna Edingen"
				}
			}
		]
}
{2000:SG Blau-Weiß Beelitz;2007:ESV Lok Sedding;2009:SpVgg Fortuna Edingen;2011}

{
    "data": [
        {
            "title": "Flyer",
            "type": "pdf",
            "url": "https://www.dropbox.com/s/j6bvrcqfze9nwo2/2013-06-29-u12-neuhof-flyer.pdf"
        }
    ],
"name":"Anhänge"
}